nanopub/__init__.py
nanopub/__main__.py
nanopub/_version.py
nanopub/client.py
nanopub/constants.py
nanopub/definitions.py
nanopub/fdo/__init__.py
nanopub/fdo/fdo_nanopub.py
nanopub/fdo/fdo_query.py
nanopub/fdo/fdo_record.py
nanopub/fdo/retrieve.py
nanopub/fdo/update.py
nanopub/fdo/utils.py
nanopub/fdo/validate.py
nanopub/namespaces.py
nanopub/nanopub.py
nanopub/nanopub_conf.py
nanopub/profile.py
nanopub/py.typed
nanopub/sign_utils.py
nanopub/templates/__init__.py
nanopub/templates/nanopub_claim.py
nanopub/templates/nanopub_index.py
nanopub/templates/nanopub_introduction.py
nanopub/templates/nanopub_retract.py
nanopub/templates/nanopub_update.py
nanopub/trustyuri/CheckFile.py
nanopub/trustyuri/ModuleDirectory.py
nanopub/trustyuri/RunBatch.py
nanopub/trustyuri/TrustyUriModule.py
nanopub/trustyuri/TrustyUriResource.py
nanopub/trustyuri/TrustyUriUtils.py
nanopub/trustyuri/__init__.py
nanopub/trustyuri/file/FileHasher.py
nanopub/trustyuri/file/FileModule.py
nanopub/trustyuri/file/ProcessFile.py
nanopub/trustyuri/file/__init__.py
nanopub/trustyuri/rdf/HashAdder.py
nanopub/trustyuri/rdf/RdfHasher.py
nanopub/trustyuri/rdf/RdfModule.py
nanopub/trustyuri/rdf/RdfPreprocessor.py
nanopub/trustyuri/rdf/RdfTransformer.py
nanopub/trustyuri/rdf/RdfUtils.py
nanopub/trustyuri/rdf/StatementComparator.py
nanopub/trustyuri/rdf/TransformRdf.py
nanopub/trustyuri/rdf/__init__.py
nanopub/utils.py
nanopub-2.1.0.dist-info/METADATA
nanopub-2.1.0.dist-info/WHEEL
nanopub-2.1.0.dist-info/entry_points.txt
nanopub-2.1.0.dist-info/licenses/LICENSE
nanopub-2.1.0.dist-info/RECORD
