Metadata-Version: 2.4
Name: nanopub
Version: 2.1.0
Summary: Python client for Nanopublications
License-File: LICENSE
Keywords: Nanopublication,RDF,Linked Data,Publishing
Author: Robin Richardson
Author-email: r.richardson@esciencecenter.nl
Requires-Python: >=3.12.0,<4.0.0
Classifier: License :: OSI Approved :: Apache Software License
Classifier: Operating System :: OS Independent
Classifier: Programming Language :: Python :: 3
Classifier: Programming Language :: Python :: 3.12
Requires-Dist: SPARQLWrapper
Requires-Dist: pycryptodome (>=3.15.0)
Requires-Dist: pyshacl
Requires-Dist: rdflib (>=6.0.2)
Requires-Dist: requests
Requires-Dist: typer
Requires-Dist: yatiml
Project-URL: Documentation, https://nanopublication.github.io/nanopub-py/
Project-URL: Homepage, https://nanopublication.github.io/nanopub-py/
Project-URL: History, https://github.com/Nanopublication/nanopub-py/releases
Project-URL: Source, https://github.com/Nanopublication/nanopub-py
Project-URL: Tracker, https://github.com/Nanopublication/nanopub-py/issues
